tests/__init__.py
tests/data.py
tests/fixtures.py
tests/test_activations.py
tests/test_apps.py
tests/test_losses.py
tests/test_metrics.py
tests/test_models.py
tests/test_threading.py
tests/test_utils.py
tests/bin/__init__.py
tests/bin/tfrecord_writer_test.py
tests/bin/train_test.py
tests/datasets/__init__.py
tests/datasets/test_dataset.py
tests/datasets/test_shapes.py
tests/datasets/test_tfrecord.py
tests/datasets/test_utils.py
tests/debug/__init__.py
tests/debug/test_export_dataset.py
tests/losses/__init__.py
tests/losses/test_utils.py
tests/processing/__init__.py
tests/processing/dataset_test.py
tests/processing/image_test.py
tests/visualizations/__init__.py
tests/visualizations/mask_test.py
tf_semantic_segmentation/__init__.py
tf_semantic_segmentation/callbacks.py
tf_semantic_segmentation/serving.py
tf_semantic_segmentation/settings.py
tf_semantic_segmentation/threading.py
tf_semantic_segmentation/utils.py
tf_semantic_segmentation/version.py
tf_semantic_segmentation/activations/__init__.py
tf_semantic_segmentation/bin/__init__.py
tf_semantic_segmentation/bin/convert_tflite.py
tf_semantic_segmentation/bin/download.py
tf_semantic_segmentation/bin/model_server_config_writer.py
tf_semantic_segmentation/bin/tfrecord_analyser.py
tf_semantic_segmentation/bin/tfrecord_download.py
tf_semantic_segmentation/bin/tfrecord_writer.py
tf_semantic_segmentation/bin/train.py
tf_semantic_segmentation/bin/train_all.py
tf_semantic_segmentation/datasets/__init__.py
tf_semantic_segmentation/datasets/ade20k.py
tf_semantic_segmentation/datasets/bioimage.py
tf_semantic_segmentation/datasets/camvid.py
tf_semantic_segmentation/datasets/cityscapes.py
tf_semantic_segmentation/datasets/cub.py
tf_semantic_segmentation/datasets/cvc_clinicdb.py
tf_semantic_segmentation/datasets/dataset.py
tf_semantic_segmentation/datasets/directory.py
tf_semantic_segmentation/datasets/isic.py
tf_semantic_segmentation/datasets/mapping_challenge.py
tf_semantic_segmentation/datasets/mots_challenge.py
tf_semantic_segmentation-0.3.1.dist-info/LICENSE
tf_semantic_segmentation-0.3.1.dist-info/METADATA
tf_semantic_segmentation-0.3.1.dist-info/WHEEL
tf_semantic_segmentation-0.3.1.dist-info/entry_points.txt
tf_semantic_segmentation-0.3.1.dist-info/top_level.txt
tf_semantic_segmentation-0.3.1.dist-info/RECORD
