Metadata-Version: 2.1
Name: tf-semantic-segmentation
Version: 0.3.1
Summary: Implementation of various semantic segmentation models in tensorflow & keras including popular datasets
Home-page: https://github.com/baudcode/tf-semantic-segmentation
Author: Malte Koch
Author-email: malte-koch@gmx.net
Maintainer: Malte Koch
Maintainer-email: malte-koch@gmx.net
License: MIT
Keywords: keras,tensorflow,tf_semantic_segmentation,semantic,segmentation,ade20k,coco,pascalvoc,cityscapes
Platform: UNKNOWN
Classifier: Development Status :: 3 - Alpha
Classifier: Intended Audience :: Developers
Classifier: Operating System :: POSIX :: Linux
Classifier: License :: OSI Approved :: GNU General Public License v3 (GPLv3)
Classifier: Programming Language :: Python :: 3
Requires-Dist: requests
Requires-Dist: imageio
Requires-Dist: opencv-python
Requires-Dist: wandb
Requires-Dist: tqdm
Requires-Dist: scipy
Requires-Dist: xmltodict
Requires-Dist: pillow
Requires-Dist: pytz
Requires-Dist: pyyaml
